Metadata-Version: 2.0
Name: eve-auth-jwt
Version: 1.0.5
Summary: Eve JWT authentication
Home-page: https://github.com/rs/eve-auth-jwt
Author: Olivier Poitrey
Author-email: rs@dailymotion.com
License: MIT
Keywords: eve,api,rest,oauth,auth,jwt
Platform: UNKNOWN
Classifier: Development Status :: 4 - Beta
Classifier: Environment :: Web Environment
Classifier: Environment :: No Input/Output (Daemon)
Classifier: Intended Audience :: Developers
Classifier: Intended Audience :: Telecommunications Industry
Classifier: License :: OSI Approved :: MIT License
Classifier: Operating System :: Unix
Classifier: Programming Language :: Python
Classifier: Programming Language :: Python :: 2.7
Classifier: Programming Language :: Python :: 3.4
Classifier: Topic :: Internet :: WWW/HTTP
Classifier: Topic :: Internet :: WWW/HTTP :: HTTP Servers
Classifier: Topic :: Security
Requires-Dist: eve (>=0.5.0)
Requires-Dist: pyjwt (==1.3.0)
